{
  "source_url": "https://en.wikipedia.org/wiki/Main_Page",
  "domain": "en.wikipedia.org",
  "title": "Wikipedia, the free encyclopedia",
  "description": "",
  "text_samples": [
    "Jump to content",
    "move to sidebar",
    "hide",
    "Search",
    "Welcome to",
    "Wikipedia",
    "free",
    "encyclopedia",
    "anyone can edit",
    "271,598",
    "7,178,585",
    "English",
    "From today's featured article",
    "Hurricane Joaquin",
    "tropical cyclone",
    "non-tropical low",
    "tropical depression",
    "Saffir\u2013Simpson scale",
    "sustained winds",
    "Acklins",
    "Crooked Island",
    "Long Island",
    "Rum Cay",
    "San Salvador Island",
    "Turks and Caicos Islands",
    "a separate storm system",
    "South Carolina",
    "Full article...",
    "Katip\u014d",
    "Maurice Suckling",
    "Shipping ethics controversy in fanfiction",
    "Archive",
    "By email",
    "More featured articles",
    "About",
    "Did you know ...",
    "... that",
    "a monument in Szczecin, Poland",
    "spirit duplicator",
    "glycerol",
    "... that, during the Middle Ages,",
    "cameline sauce",
    "Carl Grillmair",
    "exoplanets",
    "... that the"
  ],
  "image_hints": [
    "https://en.wikipedia.org/static/images/icons/enwiki-25.svg",
    "alt=Wikipedia",
    "alt=The Free Encyclopedia",
    "alt=Joaquin at peak intensity near the Bahamas",
    "alt=Duplicating Machine Memorial",
    "alt=Wu Yize in 2026",
    "alt=Christopher Smart",
    "alt=Miriam Makeba",
    "alt=Olive-bellied sunbird",
    "alt=Commons logo",
    "alt=MediaWiki logo",
    "alt=Meta-Wiki logo"
  ],
  "stylesheet_count": 2,
  "script_count": 1,
  "colors": [
    "#36c",
    "#f8f9fa",
    "#54595d",
    "rgba(0,0,0,0)",
    "#dadde3",
    "#202122",
    "#bb7070",
    "#ffdbdb",
    "#ab7f2a",
    "#fef6e7",
    "#fff",
    "#a2a9b1"
  ],
  "css_sample": "#p-lang .uls-settings-trigger{background:transparent url(/w/extensions/UniversalLanguageSelector/resources/images/cog-sprite.svg?39d1e) no-repeat center top;border:0;min-height:16px;min-width:16px;float:right;cursor:pointer}#p-lang .uls-settings-trigger::-moz-focus-inner{border:0}#p-lang .uls-settings-trigger:focus{outline:1px solid #36c}.skin-vector #p-lang .uls-settings-trigger{margin-top:8px}#p-lang .uls-settings-trigger:hover{background-position:center -16px}.client-nojs #ca-ve-edit,.ve-not-available #ca-ve-edit,.client-nojs .mw-editsection-divider,.ve-not-available .mw-editsection-divider,.client-nojs .mw-editsection-visualeditor,.ve-not-available .mw-editsection-visualeditor{display:none}.client-js .mw-editsection-bracket:first-of-type{margin-right:0.25em;margin-inline:0 0.25em}.client-js .mw-editsection-bracket:not(:first-of-type){margin-left:0.25em;margin-inline:0.25em 0}body.skin-minerva .mw-parser-output .ambox,body.skin-minerva .mw-parser-output table.ambox{display:block;margin:0}.client-js body.skin-minerva .mw-parser-output .ambox{cursor:pointer;width:auto;background:var(--background-color-interactive-subtle,#f8f9fa) !important;color:var(--color-subtle,#54595d);margin-bottom:1px}.client-js body.skin-minerva .mw-parser-output .ambox tbody{display:table;width:100%}.client-js body.skin-minerva .mw-parser-output .ambox .mbox-text-div,.client-js body.skin-minerva .mw-parser-output .ambox .mbox-text-span{display:block;max-height:3.3em;height:3.3em;overflow:hidden}.client-js body.skin-minerva .mw-parser-output .ambox div{margin:0 !important;padding:0 !important}.client-js body.skin-minerva .mw-parser-output .ambox td,.client-js body.skin-minerva .mw-parser-output .ambox div.mbox-text{position:relative;padding:8px 8px 8px 32px !important}.client-js body.skin-minerva .mw-parser-output .ambox td > div,.client-js body.skin-minerva .mw-parser-output .ambox div.mbox-text > div,.client-js body.skin-minerva .mw-parser-output .ambox td > span,.client-js body.skin-minerva .mw-parser-output .ambox div.mbox-text > span{font-size:0.8125rem}.client-js body.skin-minerva .mw-parser-output .ambox b{font-weight:inherit}.client-js body.skin-minerva .mw-parser-output .ambox a{color:inherit !important;-webkit-tap-highlight-color:rgba(0,0,0,0) !important}.client-js body.skin-minerva .mw-parser-output .ambox a:hover,.client-js body.skin-minerva .mw-parser-output .ambox a:focus{text-decoration:none;outline:inherit}.client-js body.skin-minerva .mw-parser-output .ambox small,.client-js body.skin-minerva .mw-parser-output .ambox .hide-when-compact,.client-js body.skin-minerva .mw-parser-output .ambox .mw-collapsible-content,.client-js body.skin-minerva .mw-parser-output .ambox .mbox-empty-cell,.client-js body.skin-minerva .mw-parser-output .ambox hr,.client-js body.skin-minerva .mw-parser-output .ambox .verbose,.client-js body.skin-minerva .mw-parser-output .ambox table,.client-js body.skin-minerva .mw-parser-output .ambox .mbox-image{display:none}.client-js body.skin-minerva .mw-parser-output .ambox .minerva-ambox-icon{position:absolute;left:8px;top:11px}.client-js body.skin-minerva .mw-parser-output .ambox .ambox-learn-more{color:var(--color-progressive,#36c);position:absolute;right:8px;bottom:8px;z-index:0;line-height:1.65}.client-js body.skin-minerva .mw-parser-output .ambox .ambox-learn-more::before{content:'';position:absolute;z-index:-100;bottom:0;right:0;width:100%;height:100%;box-sizing:content-box;padding-left:4em;background:linear-gradient(to right,transparent 0,var(--background-color-interactive-subtle,#f8f9fa) 3em)}@media screen and (min-width:640px){.client-js body.skin-minerva .mw-parser-output .ambox .mbox-text-div,.client-js body.skin-minerva .mw-parser-output .ambox .mbox-text-span{height:auto;margin-bottom:24px !important}.client-js body.skin-minerva .mw-parser-output .ambox .ambox-learn-more{left:32px;right:0;background:none}.client-js body.skin-minerva .mw-parser-output .ambox .ambox-learn-more::before{top:-1.65em;width:10px}}body.skin--responsive.skin-minerva .mw-parser-output .infobox{float:none !important;margin-left:0 !important;margin-right:0 !important;font-size:90%;position:relative;border:1px solid var(--border-color-muted,#dadde3);margin-bottom:2em;color:var(--color-base,#202122);background-color:var(--background-color-interactive-subtle,#f8f9fa);display:flex;flex:1 1 100%;flex-flow:column nowrap;width:100% !important;max-width:100% !important;text-align:start}body.skin--responsive.skin-minerva .mw-parser-output .infobox caption{padding:10px 10px 0;text-align:center}body.skin--responsive.skin-minerva .mw-parser-output .infobox th,body.skin--responsive.skin-minerva .mw-parser-output .infobox td{vertical-align:top;border:0;border-bottom:1px solid var(--border-color-muted,#dadde3);padding:7px 10px}body.skin--responsive.skin-minerva .mw-parser-output .infobox tbody > tr > td,body.skin--responsive.skin-minerva .mw-parser-output .infobox tbody > tr > th{flex:1 0}body.skin--responsive.skin-minerva .mw-par\ncite,dfn{font-style:inherit}q{quotes:'\"' '\"' \"'\" \"'\"}blockquote{overflow:hidden;margin:1em 0;padding:0 40px}small{font-size:85%}.mw-body-content sub,.mw-body-content sup{font-size:80%}.ns-talk .mw-body-content dd{margin-top:0.4em;margin-bottom:0.4em}.client-js .collapsible:not(.mw-made-collapsible).collapsed > tbody > tr:not(:first-child),.client-js .outercollapse .innercollapse.mw-collapsible:not(.mw-made-collapsible) > p,.client-js .outercollapse .innercollapse.mw-collapsible:not(.mw-made-collapsible) > table,.client-js .outercollapse .innercollapse.mw-collapsible:not(.mw-made-collapsible) > thead + tbody,.client-js .outercollapse .innercollapse.mw-collapsible:not(.mw-made-collapsible) tr:not(:first-child),.client-js .outercollapse .innercollapse.mw-collapsible:not(.mw-made-collapsible) .mw-collapsible-content,#editpage-specialchars{display:none}.references{margin-bottom:0.5em}span[rel=\"mw:referencedBy\"]{counter-reset:mw-ref-linkback 0}span[rel='mw:referencedBy'] > a::before{content:counter(mw-ref-linkback,lower-alpha);font-size:80%;font-weight:bold;font-style:italic}a[rel=\"mw:referencedBy\"]::before{font-weight:bold;content:\"^\"}span[rel=\"mw:referencedBy\"]::before{content:\"^ \"}.mw-parser-output .mw-collapsible-toggle:not(.mw-ui-button){font-weight:normal;padding-right:0.2em;padding-left:0.2em}.mw-collapsible-leftside-toggle .mw-collapsible-toggle{float:left}.wikitable td ul,.wikitable td ol,.wikitable td dl{text-align:left}.mw-parser-output a[href$=\".pdf\"].external,.mw-parser-output a[href*=\".pdf?\"].external,.mw-parser-output a[href*=\".pdf#\"].external,.mw-parser-output a[href$=\".PDF\"].external,.mw-parser-output a[href*=\".PDF?\"].external,.mw-parser-output a[href*=\".PDF#\"].external{background:url(//upload.wikimedia.org/wikipedia/commons/4/4d/Icon_pdf_file.png) no-repeat right;padding:8px 18px 8px 0}.mw-warning-with-logexcerpt.mw-warning-with-logexcerpt.mw-warning-with-logexcerpt,div.mw-lag-warn-high,div.mw-cascadeprotectedwarning,div#mw-protect-cascadeon{clear:both;margin:0.2em 0;border:1px solid #bb7070;background-color:var(--background-color-error-subtle,#ffdbdb);padding:0.25em 0.9em;box-sizing:border-box}.mw-contributions-blocked-notice-partial .mw-warning-with-logexcerpt.mw-warning-with-logexcerpt{border-color:var(--border-color-warning,#ab7f2a);background-color:var(--background-color-warning-subtle,#fef6e7)}@media (min-width:640px){figure[typeof~='mw:File/Thumb'],figure[typeof~='mw:File/Frame'],.thumbinner{min-width:100px}}#mw-subcategories,#mw-pages,#mw-category-media,#filehistory,#wikiPreview,#wikiDiff{clear:both}.checkuser-show,.sysop-show,.abusefilter-show,.abusefilter-helper-show,.patroller-show,.templateeditor-show,.extendedmover-show,.extendedconfirmed-show,.autoconfirmed-show,.user-show{display:none}.ve-ui-mwNoticesPopupTool-item .editnotice-redlink,.ve-ui-mwNoticesPopupTool-item .mbox-image,.ve-ui-mwNoticesPopupTool-item .mbox-imageright{display:none !important}ul.permissions-errors{margin:0}ul.permissions-errors > li{list-style:none}span.mwe-math-mathml-inline{font-size:118%}.mwe-math-fallback-image-display,.mwe-math-mathml-display{margin-left:1.6em !important;margin-top:0.6em;margin-bottom:0.6em}.mwe-math-mathml-display math{display:inline}@media screen{body:not(.ns-0):not(.ns-2):not(.ns-100) .gallerybox .thumb img{background:#fff url(//upload.wikimedia.org/wikipedia/commons/5/5d/Checker-16x16.png) repeat}#siteSub{display:block}.references{font-size:90%}}.flaggedrevs_draft_synced,.flaggedrevs_stable_synced,#t-upload,.mw-special-Book #coll-downloadbox{display:none}.infobox{border:1px solid #a2a9b1;color:black;padding:0.2em;font-size:88%;line-height:1.5em;border-spacing:3px;margin:0.5em 0}@media screen{.infobox{background-color:var(--background-color-neutral-subtle,#f8f9fa)}}@media (max-width:640px){.infobox{width:100%}.infobox .nowrap{white-space:normal}}@media (min-width:640px){.infobox{margin-left:1em;float:right;clear:right;width:22em}}.infobox-header,.infobox-label,.infobox-above,.infobox-full-data,.infobox-"
}